botanist/cycle/loops/__init__.py
botanist/cycle/loops/status_2.py
botanist/cycle/loops/status_3.py
botanist/cycle/loops/status_4.py
botanist/cycle/params/__init__.py
botanist/cycle/params/status_1.py
botanist/cycle/params/status_2.py
botanist/cycle/params_2/__init__.py
botanist/cycle/params_2/test_11.py
botanist/cycle/params_2/test_cycle_in_cycle.py
botanist/cycle/presents/__init__.py
botanist/fields/exceptions/parse.py
botanist/fields/exceptions/trace.py
botanist/fields/import/example_1/__init__.py
botanist/fields/string/end_of_string_is.py
botanist/fields/string/find_and_replace/one_character/__init__.py
botanist/fields/string/find_and_replace/one_character/test_find_and_replace.py
botanist/fields/string/find_and_replace/strand/__init__.py
botanist/fields/string/find_and_replace/strand/test_find_and_replace_string.py
botanist/fields/types/static/examples/example_1.py
botanist/modules/exceptions/parse.py
botanist/modules/fasten/__init__.py
botanist/modules/fasten/_status/example.py
botanist/modules/fasten/_status/example_caller.py
botanist/modules/fasten/_status/status_1.py
botanist/paths/directory/erase.py
botanist/ports/find_an_open_port.py
botanist/ports_v2/available.py
botanist/ports_v2/claimed.py
botanist/ports_v2/_status/test_ports.py
botanist/processes/multiple/__init__.py
botanist/processes/multiple/test_1.py
botanist/system/add_paths.py
botanist-1.0.0.dist-info/METADATA
botanist-1.0.0.dist-info/WHEEL
botanist-1.0.0.dist-info/top_level.txt
botanist-1.0.0.dist-info/RECORD
